easyros/__init__.py
easyros/__version__.py
easyros/github/__init__.py
easyros/install/__init__.py
easyros/install/install.sh
easyros/rostool/__init__.py
easyros/rostool/creat.sh
easyros/rostool/evar.py
easyros-0.0.10.dist-info/LICENSE
easyros-0.0.10.dist-info/METADATA
easyros-0.0.10.dist-info/WHEEL
easyros-0.0.10.dist-info/entry_points.txt
easyros-0.0.10.dist-info/top_level.txt
easyros-0.0.10.dist-info/RECORD
